vanillaframework/__init__.py
vanillaframework/config.py
vanillaframework/util.py
vanillaframework/management/__init__.py
vanillaframework/management/commands/__init__.py
vanillaframework/management/commands/vanillaframework.py
vanillaframework/templates/vanillaframework/tags/css.html
vanillaframework/templates/vanillaframework/tags/sass.html
vanillaframework/templatetags/vanillaframework_tags.py
django_vanillaframework-1.0.2.dist-info/LICENSE
django_vanillaframework-1.0.2.dist-info/METADATA
django_vanillaframework-1.0.2.dist-info/WHEEL
django_vanillaframework-1.0.2.dist-info/top_level.txt
django_vanillaframework-1.0.2.dist-info/RECORD
